invana_engine/__init__.py
invana_engine/server_start.py
invana_engine/settings.py
invana_engine/gremlin/__init__.py
invana_engine/gremlin/base.py
invana_engine/gremlin/client.py
invana_engine/gremlin/edge.py
invana_engine/gremlin/protocol.py
invana_engine/gremlin/schema.py
invana_engine/gremlin/stats.py
invana_engine/gremlin/vertex.py
invana_engine/gremlin/core/__init__.py
invana_engine/gremlin/core/element.py
invana_engine/gremlin/core/exceptions.py
invana_engine/gremlin/serializers/__init__.py
invana_engine/gremlin/serializers/graphson_v3.py
invana_engine/server/__init__.py
invana_engine/server/app.py
invana_engine/server/routes.py
invana_engine/server/settings.py
invana_engine/server/transport.py
invana_engine/server/utils.py
invana_engine/server/views.py
invana_engine/server/schemas/__init__.py
invana_engine/server/schemas/client.py
invana_engine/server/schemas/mutation.py
invana_engine/server/schemas/query.py
invana_engine/server/types/__init__.py
invana_engine/server/types/element.py
invana_engine/server/types/gremlin.py
tests/gql/__init__.py
tests/gql/test_gremin_query.py
tests/gremlin/__init__.py
tests/gremlin/test_client.py
tests/gremlin/test_edge.py
tests/gremlin/test_vertex.py
tests/gremlin/sample_payloads/__init__.py
tests/gremlin/sample_payloads/client.py
tests/gremlin/sample_payloads/edge.py
tests/gremlin/sample_payloads/vertex.py
invana_engine-0.0.12.dist-info/LICENSE
invana_engine-0.0.12.dist-info/METADATA
invana_engine-0.0.12.dist-info/WHEEL
invana_engine-0.0.12.dist-info/entry_points.txt
invana_engine-0.0.12.dist-info/top_level.txt
invana_engine-0.0.12.dist-info/RECORD
