Metadata-Version: 2.1
Name: invana-engine
Version: 0.0.12
Summary: GraphQL API and Insights engine for Apache TinkerPop supported graph databases.
Home-page: https://github.com/invanalabs/invana-engine
Author: Ravi Raja Merugu
Author-email: ravi@invana.io
License: UNKNOWN
Platform: UNKNOWN
Classifier: Development Status :: 3 - Alpha
Classifier: Environment :: Console
Classifier: Intended Audience :: Developers
Classifier: Topic :: Software Development :: Build Tools
Classifier: License :: OSI Approved :: Apache Software License
Classifier: Operating System :: POSIX :: Linux
Classifier: Operating System :: MacOS
Classifier: Programming Language :: Python
Classifier: Programming Language :: Python :: 3
Classifier: Programming Language :: Python :: 3.6
Classifier: Programming Language :: Python :: 3.7
Classifier: Programming Language :: Python :: 3.8
Classifier: Programming Language :: Python :: Implementation :: CPython
Classifier: Topic :: Internet :: WWW/HTTP
Classifier: Topic :: Software Development :: Libraries :: Application Frameworks
Classifier: Topic :: Software Development :: Libraries :: Python Modules
Requires-Python: >=3.6
Requires-Dist: gremlinpython (==3.4.6)
Requires-Dist: starlette (==0.13.8)
Requires-Dist: graphene (==2.1.8)
Requires-Dist: uvicorn (==0.12.2)
Requires-Dist: jinja2 (==2.11.2)
Requires-Dist: aiofiles (==0.6.0)
